CHANGELOG.md
bootloader/__init__.py
bootloader/cli/__init__.py
bootloader/cli/cmstats.py
bootloader/utils/__init__.py
bootloader/utils/plasticscm/__init__.py
bootloader/utils/plasticscm/model.py
bootloader/utils/plasticscm/reporting.py
bootloader/utils/plasticscm/utility.py
plasticscm_statistics-0.0.14.dist-info/LICENSE.md
plasticscm_statistics-0.0.14.dist-info/WHEEL
plasticscm_statistics-0.0.14.dist-info/entry_points.txt
plasticscm_statistics-0.0.14.dist-info/METADATA
plasticscm_statistics-0.0.14.dist-info/RECORD
