Metadata-Version: 2.1
Name: plasticscm-statistics
Version: 0.0.14
Summary: Python command line library to generate Plastic SCM activities reports
Home-page: https://github.com/bootloader-studio/cli-plasticscm-statistics.git
License: SEE LICENSE IN <LICENSE.md>
Keywords: library,cli,commit,changeset,plasticscm,statistics
Author: Daniel CAUNE
Author-email: daniel@bootloader.studio
Requires-Python: >=3.9,<4.0
Classifier: Development Status :: 5 - Production/Stable
Classifier: License :: Other/Proprietary License
Classifier: Operating System :: OS Independent
Classifier: Programming Language :: Python
Classifier: Programming Language :: Python :: 3
Classifier: Programming Language :: Python :: 3.9
Classifier: Programming Language :: Python :: 3.10
Classifier: Programming Language :: Python :: 3.11
Classifier: Topic :: Software Development :: Libraries
Requires-Dist: perseus-core-library (>=1.19,<2.0)
Project-URL: Repository, https://github.com/bootloader-studio/cli-plasticscm-statistics.git
